ovm_erd/__init__.py
ovm_erd/__main__.py
ovm_erd/erd_graphviz.py
ovm_erd/erd_mermaid.py
ovm_erd/main.py
ovm_erd/repo_reader.py
ovm_erd/repository_reader.py
ovm_erd/ENECO-pipeline/run_eneco.py
ovm_erd/tests/test_cli_entrypoint.py
ovm_erd/tests/test_repository_reader.py
ovm_erd-2.0.0.dist-info/licenses/LICENSE
ovm_erd-2.0.0.dist-info/METADATA
ovm_erd-2.0.0.dist-info/WHEEL
ovm_erd-2.0.0.dist-info/entry_points.txt
ovm_erd-2.0.0.dist-info/top_level.txt
ovm_erd-2.0.0.dist-info/RECORD
